pandoc_fignos.py
pandoc_fignos-2.4.0.dist-info/AUTHORS
pandoc_fignos-2.4.0.dist-info/LICENSE
pandoc_fignos-2.4.0.dist-info/METADATA
pandoc_fignos-2.4.0.dist-info/WHEEL
pandoc_fignos-2.4.0.dist-info/entry_points.txt
pandoc_fignos-2.4.0.dist-info/top_level.txt
pandoc_fignos-2.4.0.dist-info/RECORD
